zeroetl/__init__.py
zeroetl/ingestion.py
zeroetl/table_management.py
zeroetl-0.1.0.dist-info/licenses/LICENSE
zeroetl-0.1.0.dist-info/METADATA
zeroetl-0.1.0.dist-info/WHEEL
zeroetl-0.1.0.dist-info/top_level.txt
zeroetl-0.1.0.dist-info/RECORD
