Metadata-Version: 2.4
Name: zeroetl
Version: 0.1.0
Summary: A Python package for ingesting data into Iceberg tables using PySpark.
Author-email: Vibhu Dixit <vibhu.dixit02@gmail.com>
License: MIT License
Project-URL: Homepage, https://github.com/vibhu-dixit/zeroetl
Project-URL: Bug Tracker, https://github.com/vibhu-dixit/zeroetl/issues
Keywords: pyspark,iceberg,data-ingestion,etl
Classifier: Programming Language :: Python :: 3
Classifier: License :: OSI Approved :: MIT License
Classifier: Operating System :: OS Independent
Requires-Python: >=3.8
License-File: LICENSE
Requires-Dist: pyspark==3.5.1
Requires-Dist: pandas>=2.0.0
Requires-Dist: pyarrow>=15.0.0
Requires-Dist: pyiceberg[pyarrow]>=0.5.0
Requires-Dist: python-dotenv>=1.0.0
Dynamic: license-file
